<error>
	<time>06:30:20</time>
	<errornum>8</errornum>
	<type>Notice</type>
	<message>Undefined index:  MainMenu</message>
	<script>contrib\phplayersmenu\layersmenu.inc.php</script>
	<line>1341</line>
</error>
<error>
	<time>07:11:19</time>
	<errornum>2</errornum>
	<type>Warning</type>
	<message>opendir(F:\BackUp\My Documents\My Projects\enterprisecoding.com\Alumni-Online\Source Files\www\templates\skins\business008): failed to open dir: Invalid argument</message>
	<script>controls\controls.Main.php</script>
	<line>415</line>
</error>
<error>
	<time>07:11:19</time>
	<errornum>2</errornum>
	<type>Warning</type>
	<message>opendir(F:\BackUp\My Documents\My Projects\enterprisecoding.com\Alumni-Online\Source Files\www\templates\skins\business008): failed to open dir: Invalid argument</message>
	<script>controls\controls.Main.php</script>
	<line>415</line>
</error>
<error>
	<time>07:11:19</time>
	<errornum>2</errornum>
	<type>Warning</type>
	<message>filemtime(): Stat failed for F:\BackUp\My Documents\My Projects\enterprisecoding.com\Alumni-Online\Source Files\www\templates\skins\business008\index.html (errno=2 - No such file or directory)</message>
	<script>contrib\smarty\Smarty.class.php</script>
	<line>1558</line>
</error>
<error>
	<time>07:11:19</time>
	<errornum>512</errornum>
	<type>User Warning</type>
	<message>Smarty error: unable to read resource: "F:\BackUp\My Documents\My Projects\enterprisecoding.com\Alumni-Online\Source Files\www\templates\skins\business008\index.html"</message>
	<script>contrib\smarty\Smarty.class.php</script>
	<line>1102</line>
</error>
<error>
	<time>07:11:19</time>
	<errornum>2</errornum>
	<type>Warning</type>
	<message>fopen(F:\BackUp\My Documents\My Projects\enterprisecoding.com\Alumni-Online\Source Files\www\templates\skins\business008\index.html): failed to open stream: No such file or directory</message>
	<script>contrib\smarty\Smarty.class.php</script>
	<line>1728</line>
</error>
<error>
	<time>07:11:19</time>
	<errornum>2</errornum>
	<type>Warning</type>
	<message>filemtime(): Stat failed for F:\BackUp\My Documents\My Projects\enterprisecoding.com\Alumni-Online\Source Files\www\templates\skins\business008\index.html (errno=2 - No such file or directory)</message>
	<script>contrib\smarty\Smarty.class.php</script>
	<line>1558</line>
</error>
<error>
	<time>07:11:19</time>
	<errornum>512</errornum>
	<type>User Warning</type>
	<message>Smarty error: unable to read resource: "F:\BackUp\My Documents\My Projects\enterprisecoding.com\Alumni-Online\Source Files\www\templates\skins\business008\index.html"</message>
	<script>contrib\smarty\Smarty.class.php</script>
	<line>1102</line>
</error>
<error>
	<time>07:11:23</time>
	<errornum>2</errornum>
	<type>Warning</type>
	<message>opendir(F:\BackUp\My Documents\My Projects\enterprisecoding.com\Alumni-Online\Source Files\www\templates\skins\business008): failed to open dir: Invalid argument</message>
	<script>controls\controls.Main.php</script>
	<line>415</line>
</error>
<error>
	<time>07:11:23</time>
	<errornum>2</errornum>
	<type>Warning</type>
	<message>opendir(F:\BackUp\My Documents\My Projects\enterprisecoding.com\Alumni-Online\Source Files\www\templates\skins\business008): failed to open dir: Invalid argument</message>
	<script>controls\controls.Main.php</script>
	<line>415</line>
</error>
<error>
	<time>07:11:23</time>
	<errornum>2</errornum>
	<type>Warning</type>
	<message>filemtime(): Stat failed for F:\BackUp\My Documents\My Projects\enterprisecoding.com\Alumni-Online\Source Files\www\templates\skins\business008\index.html (errno=2 - No such file or directory)</message>
	<script>contrib\smarty\Smarty.class.php</script>
	<line>1558</line>
</error>
<error>
	<time>07:11:23</time>
	<errornum>512</errornum>
	<type>User Warning</type>
	<message>Smarty error: unable to read resource: "F:\BackUp\My Documents\My Projects\enterprisecoding.com\Alumni-Online\Source Files\www\templates\skins\business008\index.html"</message>
	<script>contrib\smarty\Smarty.class.php</script>
	<line>1102</line>
</error>
<error>
	<time>07:11:23</time>
	<errornum>2</errornum>
	<type>Warning</type>
	<message>fopen(F:\BackUp\My Documents\My Projects\enterprisecoding.com\Alumni-Online\Source Files\www\templates\skins\business008\index.html): failed to open stream: No such file or directory</message>
	<script>contrib\smarty\Smarty.class.php</script>
	<line>1728</line>
</error>
<error>
	<time>07:11:23</time>
	<errornum>2</errornum>
	<type>Warning</type>
	<message>filemtime(): Stat failed for F:\BackUp\My Documents\My Projects\enterprisecoding.com\Alumni-Online\Source Files\www\templates\skins\business008\index.html (errno=2 - No such file or directory)</message>
	<script>contrib\smarty\Smarty.class.php</script>
	<line>1558</line>
</error>
<error>
	<time>07:11:23</time>
	<errornum>512</errornum>
	<type>User Warning</type>
	<message>Smarty error: unable to read resource: "F:\BackUp\My Documents\My Projects\enterprisecoding.com\Alumni-Online\Source Files\www\templates\skins\business008\index.html"</message>
	<script>contrib\smarty\Smarty.class.php</script>
	<line>1102</line>
</error>
<error>
	<time>07:21:25</time>
	<errornum>2</errornum>
	<type>Warning</type>
	<message>opendir(F:\BackUp\My Documents\My Projects\enterprisecoding.com\Alumni-Online\Source Files\www\templates\skins\business008): failed to open dir: Invalid argument</message>
	<script>controls\controls.Main.php</script>
	<line>415</line>
</error>
<error>
	<time>07:21:25</time>
	<errornum>2</errornum>
	<type>Warning</type>
	<message>opendir(F:\BackUp\My Documents\My Projects\enterprisecoding.com\Alumni-Online\Source Files\www\templates\skins\business008): failed to open dir: Invalid argument</message>
	<script>controls\controls.Main.php</script>
	<line>415</line>
</error>
<error>
	<time>07:21:25</time>
	<errornum>2</errornum>
	<type>Warning</type>
	<message>filemtime(): Stat failed for F:\BackUp\My Documents\My Projects\enterprisecoding.com\Alumni-Online\Source Files\www\templates\skins\business008\index.html (errno=2 - No such file or directory)</message>
	<script>contrib\smarty\Smarty.class.php</script>
	<line>1558</line>
</error>
<error>
	<time>07:21:25</time>
	<errornum>512</errornum>
	<type>User Warning</type>
	<message>Smarty error: unable to read resource: "F:\BackUp\My Documents\My Projects\enterprisecoding.com\Alumni-Online\Source Files\www\templates\skins\business008\index.html"</message>
	<script>contrib\smarty\Smarty.class.php</script>
	<line>1102</line>
</error>
<error>
	<time>07:21:25</time>
	<errornum>2</errornum>
	<type>Warning</type>
	<message>fopen(F:\BackUp\My Documents\My Projects\enterprisecoding.com\Alumni-Online\Source Files\www\templates\skins\business008\index.html): failed to open stream: No such file or directory</message>
	<script>contrib\smarty\Smarty.class.php</script>
	<line>1728</line>
</error>
<error>
	<time>07:21:25</time>
	<errornum>2</errornum>
	<type>Warning</type>
	<message>filemtime(): Stat failed for F:\BackUp\My Documents\My Projects\enterprisecoding.com\Alumni-Online\Source Files\www\templates\skins\business008\index.html (errno=2 - No such file or directory)</message>
	<script>contrib\smarty\Smarty.class.php</script>
	<line>1558</line>
</error>
<error>
	<time>07:21:25</time>
	<errornum>512</errornum>
	<type>User Warning</type>
	<message>Smarty error: unable to read resource: "F:\BackUp\My Documents\My Projects\enterprisecoding.com\Alumni-Online\Source Files\www\templates\skins\business008\index.html"</message>
	<script>contrib\smarty\Smarty.class.php</script>
	<line>1102</line>
</error>
<error>
	<time>08:09:02</time>
	<errornum>8</errornum>
	<type>Notice</type>
	<message>Undefined offset:  4</message>
	<script>controls\customControls\admin\exceptionViewer\exceptionViewer.php</script>
	<line>61</line>
</error>
<error>
	<time>08:09:02</time>
	<errornum>8</errornum>
	<type>Notice</type>
	<message>Undefined offset:  5</message>
	<script>controls\customControls\admin\exceptionViewer\exceptionViewer.php</script>
	<line>61</line>
</error>
<error>
	<time>08:09:02</time>
	<errornum>2</errornum>
	<type>Warning</type>
	<message>fsockopen(): php_network_getaddresses: gethostbyname failed</message>
	<script>contrib\nuSoap\nusoap.php</script>
	<line>1652</line>
</error>
<error>
	<time>08:09:02</time>
	<errornum>2</errornum>
	<type>Warning</type>
	<message>fsockopen(): unable to connect to tracker.enterprisecoding.com:80</message>
	<script>contrib\nuSoap\nusoap.php</script>
	<line>1652</line>
</error>
